{
    "items": [
      {
        "id": "01",
        "name": "แบบสำรวจ B4U 1",
        "description": "แจ้งให้พนักงานทุกคนทราบว่าทางโรงพยาบาลกรุงเทพขอนแก่นจะทำการยกกเลิกการใช้แอปพลิเคชั่น"
      },
      {
        "id": "02",
        "name": "แบบสำรวจ B4U 2",
        "description": "แจ้งให้พนักงานทุกคนทราบว่าทางโรงพยาบาลกรุงเทพขอนแก่นจะทำการยกกเลิกการใช้แอปพลิเคชั่น"
      },
      {
        "id": "03",
        "name": "แบบสำรวจ B4U 3",
        "description": "แจ้งให้พนักงานทุกคนทราบว่าทางโรงพยาบาลกรุงเทพขอนแก่นจะทำการยกกเลิกการใช้แอปพลิเคชั่น"
      }
    ]
  }